<Namespace Name="System.Security.Authentication.ExtendedProtection.Configuration">
  <Docs>
    <summary>Provides support for configuration of authentication using extended protection for applications.</summary>
    <remarks>To be added.</remarks>
    <altmember cref="N:System.Security.Authentication.ExtendedProtection" />
    <related type="Article" href="/dotnet/framework/network-programming/integrated-windows-authentication-with-extended-protection">Integrated Windows Authentication with Extended Protection</related>
  </Docs>
</Namespace>
